 [{
    "fmid":1006415,
    "marketname":"Wooster's Grove Farmers Market",
    "website":"http://www.villageofwalden.org",
    "street":"89 East Main Street (Route 52E)",
    "city":"Walden",
    "county":"Orange",
    "state":"New York",
    "zip":"12586",
    "season1date":"June to October",
    "season1time":"Fri:1:00 PM - 5:30 PM;",
    "season2date":"",
    "season2time":"",
    "season3date":"",
    "season3time":"",
    "season4date":"",
    "season4time":"",
    "x":-74.188625,
    "y":41.559749,
    "location":"Local government building grounds",
    "credit":"Y",
    "wic":"N",
    "wiccash":"N",
    "sfmnp":"Y",
    "snap":"Y",
    "bakedgoods":"Y",
    "cheese":"Y",
    "crafts":"Y",
    "flowers":"Y",
    "eggs":"N",
    "seafood":"N",
    "herbs":"Y",
    "vegetables":"Y",
    "honey":"Y",
    "jams":"Y",
    "maple":"N",
    "meat":"N",
    "nursery":"Y",
    "nuts":"N",
    "plants":"N",
    "poultry":"N",
    "prepared":"Y",
    "soap":"Y",
    "trees":"N",
    "wine":"Y",
    "updatetime":"6/1/12 9:59"
  }]